{
  "date": "2026-03-12",
  "errors": [
    {
      "error": "Could not find price for arbitrum",
      "source": "yahoo"
    }
  ],
  "fetched_at": "2026-03-12T02:06:05.810803+00:00",
  "quotes": [
    {
      "currency": "USD",
      "name": "Bitcoin",
      "price": 69810.84,
      "raw": "$69,810.84",
      "slug": "bitcoin",
      "source": "coingecko",
      "symbol": "BTC",
      "url": "https://www.coingecko.com/"
    },
    {
      "currency": "USD",
      "name": "Ethereum",
      "price": 2045.28,
      "raw": "$2,045.28",
      "slug": "ethereum",
      "source": "coingecko",
      "symbol": "ETH",
      "url": "https://www.coingecko.com/"
    },
    {
      "currency": "USD",
      "name": "Solana",
      "price": 86.01,
      "raw": "$86.01",
      "slug": "solana",
      "source": "coingecko",
      "symbol": "SOL",
      "url": "https://www.coingecko.com/"
    },
    {
      "currency": "USD",
      "name": "Cardano",
      "price": 0.2608,
      "raw": "$0.2608",
      "slug": "cardano",
      "source": "coingecko",
      "symbol": "ADA",
      "url": "https://www.coingecko.com/"
    },
    {
      "currency": "USD",
      "name": "Arbitrum",
      "price": 0.09979,
      "raw": "$0.09979",
      "slug": "arbitrum",
      "source": "coingecko",
      "symbol": "ARB",
      "url": "https://www.coingecko.com/"
    },
    {
      "currency": "USD",
      "name": "Monero",
      "price": 350.66,
      "raw": "$350.66",
      "slug": "monero",
      "source": "coingecko",
      "symbol": "XMR",
      "url": "https://www.coingecko.com/"
    },
    {
      "currency": "USD",
      "name": "BNB",
      "price": 646.83,
      "raw": "$646.83",
      "slug": "binancecoin",
      "source": "coingecko",
      "symbol": "BNB",
      "url": "https://www.coingecko.com/"
    },
    {
      "currency": "EUR",
      "name": "Bitcoin",
      "price": 60438.0,
      "raw": "\u20ac60,438.00",
      "slug": "bitcoin",
      "source": "kraken",
      "symbol": "BTC",
      "url": "https://www.kraken.com/prices"
    },
    {
      "currency": "EUR",
      "name": "Ethereum",
      "price": 1770.57,
      "raw": "\u20ac1,770.57",
      "slug": "ethereum",
      "source": "kraken",
      "symbol": "ETH",
      "url": "https://www.kraken.com/prices"
    },
    {
      "currency": "EUR",
      "name": "Solana",
      "price": 74.46,
      "raw": "\u20ac74.46",
      "slug": "solana",
      "source": "kraken",
      "symbol": "SOL",
      "url": "https://www.kraken.com/prices"
    },
    {
      "currency": "EUR",
      "name": "Cardano",
      "price": 0.23,
      "raw": "\u20ac0.23",
      "slug": "cardano",
      "source": "kraken",
      "symbol": "ADA",
      "url": "https://www.kraken.com/prices"
    },
    {
      "currency": "EUR",
      "name": "Arbitrum",
      "price": 0.086,
      "raw": "\u20ac0.086",
      "slug": "arbitrum",
      "source": "kraken",
      "symbol": "ARB",
      "url": "https://www.kraken.com/prices"
    },
    {
      "currency": "EUR",
      "name": "Monero",
      "price": 303.56,
      "raw": "\u20ac303.56",
      "slug": "monero",
      "source": "kraken",
      "symbol": "XMR",
      "url": "https://www.kraken.com/prices"
    },
    {
      "currency": "EUR",
      "name": "BNB",
      "price": 559.98,
      "raw": "\u20ac559.98",
      "slug": "binancecoin",
      "source": "kraken",
      "symbol": "BNB",
      "url": "https://www.kraken.com/prices"
    },
    {
      "currency": "USD",
      "name": "Bitcoin",
      "price": 69854.8,
      "raw": "$69,854.80",
      "slug": "bitcoin",
      "source": "kraken",
      "symbol": "BTC",
      "url": "https://www.kraken.com/prices"
    },
    {
      "currency": "USD",
      "name": "Ethereum",
      "price": 2045.12,
      "raw": "$2,045.12",
      "slug": "ethereum",
      "source": "kraken",
      "symbol": "ETH",
      "url": "https://www.kraken.com/prices"
    },
    {
      "currency": "USD",
      "name": "Solana",
      "price": 86.05,
      "raw": "$86.05",
      "slug": "solana",
      "source": "kraken",
      "symbol": "SOL",
      "url": "https://www.kraken.com/prices"
    },
    {
      "currency": "USD",
      "name": "Cardano",
      "price": 0.26,
      "raw": "$0.26",
      "slug": "cardano",
      "source": "kraken",
      "symbol": "ADA",
      "url": "https://www.kraken.com/prices"
    },
    {
      "currency": "USD",
      "name": "Arbitrum",
      "price": 0.1,
      "raw": "$0.100",
      "slug": "arbitrum",
      "source": "kraken",
      "symbol": "ARB",
      "url": "https://www.kraken.com/prices"
    },
    {
      "currency": "USD",
      "name": "Monero",
      "price": 350.49,
      "raw": "$350.49",
      "slug": "monero",
      "source": "kraken",
      "symbol": "XMR",
      "url": "https://www.kraken.com/prices"
    },
    {
      "currency": "USD",
      "name": "BNB",
      "price": 646.64,
      "raw": "$646.64",
      "slug": "binancecoin",
      "source": "kraken",
      "symbol": "BNB",
      "url": "https://www.kraken.com/prices"
    },
    {
      "currency": "USDT",
      "name": "Bitcoin",
      "price": 69837.46,
      "raw": "69837.46",
      "slug": "bitcoin",
      "source": "binance",
      "symbol": "BTC",
      "url": "https://www.binance.com/en/markets/overview"
    },
    {
      "currency": "USDT",
      "name": "Cardano",
      "price": 0.261,
      "raw": "0.2610",
      "slug": "cardano",
      "source": "binance",
      "symbol": "ADA",
      "url": "https://www.binance.com/en/markets/overview"
    },
    {
      "currency": "USDT",
      "name": "Solana",
      "price": 86.06,
      "raw": "86.06",
      "slug": "solana",
      "source": "binance",
      "symbol": "SOL",
      "url": "https://www.binance.com/en/markets/overview"
    },
    {
      "currency": "USDT",
      "name": "BNB",
      "price": 647.22,
      "raw": "647.22",
      "slug": "binancecoin",
      "source": "binance",
      "symbol": "BNB",
      "url": "https://www.binance.com/en/markets/overview"
    },
    {
      "currency": "USDT",
      "name": "Ethereum",
      "price": 2045.35,
      "raw": "2045.35",
      "slug": "ethereum",
      "source": "binance",
      "symbol": "ETH",
      "url": "https://www.binance.com/en/markets/overview"
    },
    {
      "currency": "USDT",
      "name": "Arbitrum",
      "price": 0.0999,
      "raw": "0.0999",
      "slug": "arbitrum",
      "source": "binance",
      "symbol": "ARB",
      "url": "https://www.binance.com/en/markets/overview"
    },
    {
      "currency": "USD",
      "name": "Bitcoin",
      "price": 69841.84,
      "raw": "$69,841.84",
      "slug": "bitcoin",
      "source": "coinmarketcap",
      "symbol": "BTC",
      "url": "https://coinmarketcap.com/"
    },
    {
      "currency": "USD",
      "name": "Ethereum",
      "price": 2045.99,
      "raw": "$2,045.99",
      "slug": "ethereum",
      "source": "coinmarketcap",
      "symbol": "ETH",
      "url": "https://coinmarketcap.com/"
    },
    {
      "currency": "USD",
      "name": "Solana",
      "price": 86.04,
      "raw": "$86.04",
      "slug": "solana",
      "source": "coinmarketcap",
      "symbol": "SOL",
      "url": "https://coinmarketcap.com/"
    },
    {
      "currency": "USD",
      "name": "Cardano",
      "price": 0.2607,
      "raw": "$0.2607",
      "slug": "cardano",
      "source": "coinmarketcap",
      "symbol": "ADA",
      "url": "https://coinmarketcap.com/"
    },
    {
      "currency": "USD",
      "name": "Arbitrum",
      "price": 0.1,
      "raw": "$0.10",
      "slug": "arbitrum",
      "source": "coinmarketcap",
      "symbol": "ARB",
      "url": "https://coinmarketcap.com/"
    },
    {
      "currency": "USD",
      "name": "Monero",
      "price": 350.42,
      "raw": "$350.42",
      "slug": "monero",
      "source": "coinmarketcap",
      "symbol": "XMR",
      "url": "https://coinmarketcap.com/"
    },
    {
      "currency": "USD",
      "name": "BNB",
      "price": 647.93,
      "raw": "$647.93",
      "slug": "binancecoin",
      "source": "coinmarketcap",
      "symbol": "BNB",
      "url": "https://coinmarketcap.com/"
    },
    {
      "currency": "USD",
      "name": "Bitcoin",
      "price": 69811.84,
      "raw": "$69,811.84",
      "slug": "bitcoin",
      "source": "coindesk",
      "symbol": "BTC",
      "url": "https://www.coindesk.com/price"
    },
    {
      "currency": "USD",
      "name": "Ethereum",
      "price": 2045.52,
      "raw": "$2,045.52",
      "slug": "ethereum",
      "source": "coindesk",
      "symbol": "ETH",
      "url": "https://www.coindesk.com/price"
    },
    {
      "currency": "USD",
      "name": "BNB",
      "price": 647.17,
      "raw": "$647.17",
      "slug": "binancecoin",
      "source": "coindesk",
      "symbol": "BNB",
      "url": "https://www.coindesk.com/price"
    },
    {
      "currency": "USD",
      "name": "Solana",
      "price": 86.01,
      "raw": "$86.01",
      "slug": "solana",
      "source": "coindesk",
      "symbol": "SOL",
      "url": "https://www.coindesk.com/price"
    },
    {
      "currency": "USD",
      "name": "Cardano",
      "price": 0.2607,
      "raw": "$0.2607",
      "slug": "cardano",
      "source": "coindesk",
      "symbol": "ADA",
      "url": "https://www.coindesk.com/price"
    },
    {
      "currency": "USD",
      "name": "Monero",
      "price": 350.73,
      "raw": "$350.73",
      "slug": "monero",
      "source": "coindesk",
      "symbol": "XMR",
      "url": "https://www.coindesk.com/price"
    }
  ],
  "sources": [
    "coingecko",
    "kraken",
    "yahoo",
    "binance",
    "coinmarketcap",
    "coindesk"
  ]
}
